setup.py
CarrollPiProject/DissolvedOxygen.py
CarrollPiProject/Temperature.py
CarrollPiProject/Website.py
CarrollPiProject/__init__.py
CarrollPiProject.egg-info/PKG-INFO
CarrollPiProject.egg-info/SOURCES.txt
CarrollPiProject.egg-info/dependency_links.txt
CarrollPiProject.egg-info/not-zip-safe
CarrollPiProject.egg-info/top_level.txt