Metadata-Version: 1.0
Name: CarrollPiProject
Version: 0.2.2
Summary: Functions for interacting with the Pi using the sensors and sending data to the CarrollPiProject website.
Home-page: https://github.com/CarrollPiProject/CarrollPiProject
Author: Carroll Pi Project: NC Division
Author-email: ncscienceresearch@gmail.com
License: MIT
Platform: UNKNOWN
